{
  "Common": {
    "CustomerAfftectedCount": 699,
    "OutageCount": 13,
    "LastUpdatedDatetime": "07/17 05:44 PM"
  },
  "CustomerProfile": null,
  "PseMap": [
    {
      "DataProvider": {
        "Attributes": [
          {
            "Name": "Start time",
            "Value": "07/17 03:02 PM",
            "NoDisplay": false
          },
          {
            "Name": "Customers impacted",
            "Value": "2",
            "NoDisplay": false
          },
          {
            "Name": "Status",
            "Value": "Repair crew onsite",
            "NoDisplay": false
          },
          {
            "Name": "Cause",
            "Value": "Equipment Failure",
            "NoDisplay": false
          },
          {
            "Name": "Last update",
            "Value": "07/17 05:40 PM",
            "NoDisplay": false
          },
          {
            "Name": "Est. restoration time",
            "Value": "07/17 06:00 PM",
            "NoDisplay": false
          }
        ],
        "PointOfInterest": {
          "Latitude": "47.63260",
          "Longitude": "-122.50606",
          "MapType": "Outage",
          "PinType": "Outage",
          "Title": "Bainbridge Island",
          "Id": "911216",
          "PlannedOutage": false
        }
      },
      "Polygon": [
        {
          "Latitude": "47.63260",
          "Longitude": "-122.50599"
        },
        {
          "Latitude": "47.63260",
          "Longitude": "-122.50599"
        },
        {
          "Latitude": "47.63259",
          "Longitude": "-122.50599"
        },
        {
          "Latitude": "47.63258",
          "Longitude": "-122.50600"
        },
        {
          "Latitude": "47.63257",
          "Longitude": "-122.50601"
        },
        {
          "Latitude": "47.63257",
          "Longitude": "-122.50602"
        },
        {
          "Latitude": "47.63256",
          "Longitude": "-122.50603"
        },
        {
          "Latitude": "47.63256",
          "Longitude": "-122.50604"
        },
        {
          "Latitude": "47.63256",
          "Longitude": "-122.50605"
        },
        {
          "Latitude": "47.63256",
          "Longitude": "-122.50607"
        },
        {
          "Latitude": "47.63256",
          "Longitude": "-122.50608"
        },
        {
          "Latitude": "47.63257",
          "Longitude": "-122.50609"
        },
        {
          "Latitude": "47.63257",
          "Longitude": "-122.50610"
        },
        {
          "Latitude": "47.63258",
          "Longitude": "-122.50611"
        },
        {
          "Latitude": "47.63259",
          "Longitude": "-122.50612"
        },
        {
          "Latitude": "47.63259",
          "Longitude": "-122.50612"
        },
        {
          "Latitude": "47.63260",
          "Longitude": "-122.50612"
        },
        {
          "Latitude": "47.63261",
          "Longitude": "-122.50612"
        },
        {
          "Latitude": "47.63262",
          "Longitude": "-122.50612"
        },
        {
          "Latitude": "47.63263",
          "Longitude": "-122.50611"
        },
        {
          "Latitude": "47.63263",
          "Longitude": "-122.50610"
        },
        {
          "Latitude": "47.63264",
          "Longitude": "-122.50609"
        },
        {
          "Latitude": "47.63265",
          "Longitude": "-122.50608"
        },
        {
          "Latitude": "47.63265",
          "Longitude": "-122.50607"
        },
        {
          "Latitude": "47.63265",
          "Longitude": "-122.50606"
        },
        {
          "Latitude": "47.63265",
          "Longitude": "-122.50604"
        },
        {
          "Latitude": "47.63265",
          "Longitude": "-122.50603"
        },
        {
          "Latitude": "47.63264",
          "Longitude": "-122.50602"
        },
        {
          "Latitude": "47.63264",
          "Longitude": "-122.50601"
        },
        {
          "Latitude": "47.63263",
          "Longitude": "-122.50600"
        },
        {
          "Latitude": "47.63262",
          "Longitude": "-122.50599"
        },
        {
          "Latitude": "47.63261",
          "Longitude": "-122.50599"
        },
        {
          "Latitude": "47.63260",
          "Longitude": "-122.50599"
        }
      ],
      "BoundingBox": {
        "Min": {
          "Latitude": "47.63256",
          "Longitude": "-122.50612"
        },
        "Max": {
          "Latitude": "47.63265",
          "Longitude": "-122.50599"
        }
      }
    },
    {
      "DataProvider": {
        "Attributes": [
          {
            "Name": "Start time",
            "Value": "07/17 04:23 PM",
            "NoDisplay": false
          },
          {
            "Name": "Customers impacted",
            "Value": "2",
            "NoDisplay": false
          },
          {
            "Name": "Status",
            "Value": "Crew assigned",
            "NoDisplay": false
          },
          {
            "Name": "Cause",
            "Value": "Trees/Vegetation",
            "NoDisplay": false
          },
          {
            "Name": "Last update",
            "Value": "07/17 05:40 PM",
            "NoDisplay": false
          },
          {
            "Name": "Est. restoration time",
            "Value": "07/17 06:30 PM",
            "NoDisplay": false
          }
        ],
        "PointOfInterest": {
          "Latitude": "47.32718",
          "Longitude": "-122.37789",
          "MapType": "Outage",
          "PinType": "Outage",
          "Title": "Federal Way",
          "Id": "911433",
          "PlannedOutage": false
        }
      },
      "Polygon": [
        {
          "Latitude": "47.32718",
          "Longitude": "-122.37783"
        },
        {
          "Latitude": "47.32717",
          "Longitude": "-122.37783"
        },
        {
          "Latitude": "47.32716",
          "Longitude": "-122.37783"
        },
        {
          "Latitude": "47.32715",
          "Longitude": "-122.37784"
        },
        {
          "Latitude": "47.32715",
          "Longitude": "-122.37784"
        },
        {
          "Latitude": "47.32714",
          "Longitude": "-122.37785"
        },
        {
          "Latitude": "47.32714",
          "Longitude": "-122.37786"
        },
        {
          "Latitude": "47.32713",
          "Longitude": "-122.37788"
        },
        {
          "Latitude": "47.32713",
          "Longitude": "-122.37789"
        },
        {
          "Latitude": "47.32713",
          "Longitude": "-122.37790"
        },
        {
          "Latitude": "47.32714",
          "Longitude": "-122.37792"
        },
        {
          "Latitude": "47.32714",
          "Longitude": "-122.37793"
        },
        {
          "Latitude": "47.32714",
          "Longitude": "-122.37794"
        },
        {
          "Latitude": "47.32715",
          "Longitude": "-122.37795"
        },
        {
          "Latitude": "47.32716",
          "Longitude": "-122.37795"
        },
        {
          "Latitude": "47.32717",
          "Longitude": "-122.37796"
        },
        {
          "Latitude": "47.32718",
          "Longitude": "-122.37796"
        },
        {
          "Latitude": "47.32719",
          "Longitude": "-122.37796"
        },
        {
          "Latitude": "47.32719",
          "Longitude": "-122.37795"
        },
        {
          "Latitude": "47.32720",
          "Longitude": "-122.37795"
        },
        {
          "Latitude": "47.32721",
          "Longitude": "-122.37794"
        },
        {
          "Latitude": "47.32721",
          "Longitude": "-122.37793"
        },
        {
          "Latitude": "47.32722",
          "Longitude": "-122.37792"
        },
        {
          "Latitude": "47.32722",
          "Longitude": "-122.37791"
        },
        {
          "Latitude": "47.32722",
          "Longitude": "-122.37789"
        },
        {
          "Latitude": "47.32722",
          "Longitude": "-122.37788"
        },
        {
          "Latitude": "47.32722",
          "Longitude": "-122.37787"
        },
        {
          "Latitude": "47.32722",
          "Longitude": "-122.37786"
        },
        {
          "Latitude": "47.32721",
          "Longitude": "-122.37785"
        },
        {
          "Latitude": "47.32720",
          "Longitude": "-122.37784"
        },
        {
          "Latitude": "47.32720",
          "Longitude": "-122.37783"
        },
        {
          "Latitude": "47.32719",
          "Longitude": "-122.37783"
        },
        {
          "Latitude": "47.32718",
          "Longitude": "-122.37783"
        }
      ],
      "BoundingBox": {
        "Min": {
          "Latitude": "47.32713",
          "Longitude": "-122.37796"
        },
        "Max": {
          "Latitude": "47.32722",
          "Longitude": "-122.37783"
        }
      }
    },
    {
      "DataProvider": {
        "Attributes": [
          {
            "Name": "Start time",
            "Value": "07/17 12:07 PM",
            "NoDisplay": false
          },
          {
            "Name": "Customers impacted",
            "Value": "3",
            "NoDisplay": false
          },
          {
            "Name": "Status",
            "Value": "Crew assigned",
            "NoDisplay": false
          },
          {
            "Name": "Cause",
            "Value": "Equipment Failure",
            "NoDisplay": false
          },
          {
            "Name": "Last update",
            "Value": "07/17 05:40 PM",
            "NoDisplay": false
          },
          {
            "Name": "Est. restoration time",
            "Value": "07/17 07:30 PM",
            "NoDisplay": false
          }
        ],
        "PointOfInterest": {
          "Latitude": "47.40731",
          "Longitude": "-122.18173",
          "MapType": "Outage",
          "PinType": "Outage",
          "Title": "Kent",
          "Id": "911374",
          "PlannedOutage": false
        }
      },
      "Polygon": [
        {
          "Latitude": "47.40744",
          "Longitude": "-122.18168"
        },
        {
          "Latitude": "47.40745",
          "Longitude": "-122.18167"
        },
        {
          "Latitude": "47.40745",
          "Longitude": "-122.18166"
        },
        {
          "Latitude": "47.40746",
          "Longitude": "-122.18165"
        },
        {
          "Latitude": "47.40746",
          "Longitude": "-122.18164"
        },
        {
          "Latitude": "47.40746",
          "Longitude": "-122.18162"
        },
        {
          "Latitude": "47.40746",
          "Longitude": "-122.18161"
        },
        {
          "Latitude": "47.40746",
          "Longitude": "-122.18160"
        },
        {
          "Latitude": "47.40745",
          "Longitude": "-122.18159"
        },
        {
          "Latitude": "47.40745",
          "Longitude": "-122.18158"
        },
        {
          "Latitude": "47.40744",
          "Longitude": "-122.18157"
        },
        {
          "Latitude": "47.40743",
          "Longitude": "-122.18156"
        },
        {
          "Latitude": "47.40743",
          "Longitude": "-122.18156"
        },
        {
          "Latitude": "47.40742",
          "Longitude": "-122.18156"
        },
        {
          "Latitude": "47.40741",
          "Longitude": "-122.18156"
        },
        {
          "Latitude": "47.40740",
          "Longitude": "-122.18156"
        },
        {
          "Latitude": "47.40739",
          "Longitude": "-122.18157"
        },
        {
          "Latitude": "47.40719",
          "Longitude": "-122.18177"
        },
        {
          "Latitude": "47.40718",
          "Longitude": "-122.18178"
        },
        {
          "Latitude": "47.40718",
          "Longitude": "-122.18179"
        },
        {
          "Latitude": "47.40717",
          "Longitude": "-122.18180"
        },
        {
          "Latitude": "47.40717",
          "Longitude": "-122.18181"
        },
        {
          "Latitude": "47.40717",
          "Longitude": "-122.18183"
        },
        {
          "Latitude": "47.40717",
          "Longitude": "-122.18184"
        },
        {
          "Latitude": "47.40717",
          "Longitude": "-122.18185"
        },
        {
          "Latitude": "47.40718",
          "Longitude": "-122.18186"
        },
        {
          "Latitude": "47.40718",
          "Longitude": "-122.18187"
        },
        {
          "Latitude": "47.40719",
          "Longitude": "-122.18188"
        },
        {
          "Latitude": "47.40720",
          "Longitude": "-122.18189"
        },
        {
          "Latitude": "47.40721",
          "Longitude": "-122.18189"
        },
        {
          "Latitude": "47.40721",
          "Longitude": "-122.18189"
        },
        {
          "Latitude": "47.40722",
          "Longitude": "-122.18189"
        },
        {
          "Latitude": "47.40723",
          "Longitude": "-122.18189"
        },
        {
          "Latitude": "47.40724",
          "Longitude": "-122.18188"
        },
        {
          "Latitude": "47.40744",
          "Longitude": "-122.18168"
        }
      ],
      "BoundingBox": {
        "Min": {
          "Latitude": "47.40717",
          "Longitude": "-122.18189"
        },
        "Max": {
          "Latitude": "47.40746",
          "Longitude": "-122.18156"
        }
      }
    },
    {
      "DataProvider": {
        "Attributes": [
          {
            "Name": "Start time",
            "Value": "07/17 05:07 PM",
            "NoDisplay": false
          },
          {
            "Name": "Customers impacted",
            "Value": "2",
            "NoDisplay": false
          },
          {
            "Name": "Status",
            "Value": "Waiting for repairs",
            "NoDisplay": false
          },
          {
            "Name": "Cause",
            "Value": "Trees/Vegetation",
            "NoDisplay": false
          },
          {
            "Name": "Last update",
            "Value": "07/17 05:40 PM",
            "NoDisplay": false
          },
          {
            "Name": "Est. restoration time",
            "Value": "To Be Determined",
            "NoDisplay": false
          }
        ],
        "PointOfInterest": {
          "Latitude": "47.81071",
          "Longitude": "-122.57257",
          "MapType": "Outage",
          "PinType": "Outage",
          "Title": "Kingston",
          "Id": "911431",
          "PlannedOutage": false
        }
      },
      "Polygon": [
        {
          "Latitude": "47.81093",
          "Longitude": "-122.57273"
        },
        {
          "Latitude": "47.81094",
          "Longitude": "-122.57273"
        },
        {
          "Latitude": "47.81095",
          "Longitude": "-122.57273"
        },
        {
          "Latitude": "47.81096",
          "Longitude": "-122.57273"
        },
        {
          "Latitude": "47.81096",
          "Longitude": "-122.57272"
        },
        {
          "Latitude": "47.81097",
          "Longitude": "-122.57271"
        },
        {
          "Latitude": "47.81098",
          "Longitude": "-122.57271"
        },
        {
          "Latitude": "47.81098",
          "Longitude": "-122.57269"
        },
        {
          "Latitude": "47.81099",
          "Longitude": "-122.57268"
        },
        {
          "Latitude": "47.81099",
          "Longitude": "-122.57267"
        },
        {
          "Latitude": "47.81099",
          "Longitude": "-122.57266"
        },
        {
          "Latitude": "47.81099",
          "Longitude": "-122.57264"
        },
        {
          "Latitude": "47.81098",
          "Longitude": "-122.57263"
        },
        {
          "Latitude": "47.81098",
          "Longitude": "-122.57262"
        },
        {
          "Latitude": "47.81097",
          "Longitude": "-122.57261"
        },
        {
          "Latitude": "47.81096",
          "Longitude": "-122.57260"
        },
        {
          "Latitude": "47.81095",
          "Longitude": "-122.57260"
        },
        {
          "Latitude": "47.81049",
          "Longitude": "-122.57241"
        },
        {
          "Latitude": "47.81048",
          "Longitude": "-122.57241"
        },
        {
          "Latitude": "47.81047",
          "Longitude": "-122.57241"
        },
        {
          "Latitude": "47.81046",
          "Longitude": "-122.57241"
        },
        {
          "Latitude": "47.81046",
          "Longitude": "-122.57242"
        },
        {
          "Latitude": "47.81045",
          "Longitude": "-122.57242"
        },
        {
          "Latitude": "47.81044",
          "Longitude": "-122.57243"
        },
        {
          "Latitude": "47.81044",
          "Longitude": "-122.57244"
        },
        {
          "Latitude": "47.81044",
          "Longitude": "-122.57246"
        },
        {
          "Latitude": "47.81043",
          "Longitude": "-122.57247"
        },
        {
          "Latitude": "47.81043",
          "Longitude": "-122.57248"
        },
        {
          "Latitude": "47.81044",
          "Longitude": "-122.57250"
        },
        {
          "Latitude": "47.81044",
          "Longitude": "-122.57251"
        },
        {
          "Latitude": "47.81045",
          "Longitude": "-122.57252"
        },
        {
          "Latitude": "47.81045",
          "Longitude": "-122.57253"
        },
        {
          "Latitude": "47.81046",
          "Longitude": "-122.57253"
        },
        {
          "Latitude": "47.81047",
          "Longitude": "-122.57254"
        },
        {
          "Latitude": "47.81093",
          "Longitude": "-122.57273"
        }
      ],
      "BoundingBox": {
        "Min": {
          "Latitude": "47.81043",
          "Longitude": "-122.57273"
        },
        "Max": {
          "Latitude": "47.81099",
          "Longitude": "-122.57241"
        }
      }
    },
    {
      "DataProvider": {
        "Attributes": [
          {
            "Name": "Start time",
            "Value": "07/17 05:30 PM",
            "NoDisplay": false
          },
          {
            "Name": "Customers impacted",
            "Value": "2",
            "NoDisplay": false
          },
          {
            "Name": "Status",
            "Value": "Outage reported",
            "NoDisplay": false
          },
          {
            "Name": "Cause",
            "Value": "Under Investigation",
            "NoDisplay": false
          },
          {
            "Name": "Last update",
            "Value": "07/17 05:40 PM",
            "NoDisplay": false
          },
          {
            "Name": "Est. restoration time",
            "Value": "07/17 07:30 PM",
            "NoDisplay": false
          }
        ],
        "PointOfInterest": {
          "Latitude": "48.09086",
          "Longitude": "-122.50530",
          "MapType": "Outage",
          "PinType": "Outage",
          "Title": "Langley",
          "Id": "911460",
          "PlannedOutage": false
        }
      },
      "Polygon": [
        {
          "Latitude": "48.09038",
          "Longitude": "-122.50483"
        },
        {
          "Latitude": "48.09037",
          "Longitude": "-122.50482"
        },
        {
          "Latitude": "48.09036",
          "Longitude": "-122.50482"
        },
        {
          "Latitude": "48.09035",
          "Longitude": "-122.50482"
        },
        {
          "Latitude": "48.09034",
          "Longitude": "-122.50482"
        },
        {
          "Latitude": "48.09034",
          "Longitude": "-122.50483"
        },
        {
          "Latitude": "48.09033",
          "Longitude": "-122.50483"
        },
        {
          "Latitude": "48.09032",
          "Longitude": "-122.50484"
        },
        {
          "Latitude": "48.09032",
          "Longitude": "-122.50485"
        },
        {
          "Latitude": "48.09031",
          "Longitude": "-122.50487"
        },
        {
          "Latitude": "48.09031",
          "Longitude": "-122.50488"
        },
        {
          "Latitude": "48.09031",
          "Longitude": "-122.50489"
        },
        {
          "Latitude": "48.09031",
          "Longitude": "-122.50491"
        },
        {
          "Latitude": "48.09032",
          "Longitude": "-122.50492"
        },
        {
          "Latitude": "48.09032",
          "Longitude": "-122.50493"
        },
        {
          "Latitude": "48.09033",
          "Longitude": "-122.50494"
        },
        {
          "Latitude": "48.09033",
          "Longitude": "-122.50495"
        },
        {
          "Latitude": "48.09134",
          "Longitude": "-122.50578"
        },
        {
          "Latitude": "48.09134",
          "Longitude": "-122.50579"
        },
        {
          "Latitude": "48.09135",
          "Longitude": "-122.50579"
        },
        {
          "Latitude": "48.09136",
          "Longitude": "-122.50579"
        },
        {
          "Latitude": "48.09137",
          "Longitude": "-122.50579"
        },
        {
          "Latitude": "48.09138",
          "Longitude": "-122.50578"
        },
        {
          "Latitude": "48.09139",
          "Longitude": "-122.50577"
        },
        {
          "Latitude": "48.09139",
          "Longitude": "-122.50577"
        },
        {
          "Latitude": "48.09140",
          "Longitude": "-122.50575"
        },
        {
          "Latitude": "48.09140",
          "Longitude": "-122.50574"
        },
        {
          "Latitude": "48.09140",
          "Longitude": "-122.50573"
        },
        {
          "Latitude": "48.09140",
          "Longitude": "-122.50572"
        },
        {
          "Latitude": "48.09140",
          "Longitude": "-122.50570"
        },
        {
          "Latitude": "48.09140",
          "Longitude": "-122.50569"
        },
        {
          "Latitude": "48.09139",
          "Longitude": "-122.50568"
        },
        {
          "Latitude": "48.09139",
          "Longitude": "-122.50567"
        },
        {
          "Latitude": "48.09138",
          "Longitude": "-122.50566"
        },
        {
          "Latitude": "48.09038",
          "Longitude": "-122.50483"
        }
      ],
      "BoundingBox": {
        "Min": {
          "Latitude": "48.09031",
          "Longitude": "-122.50579"
        },
        "Max": {
          "Latitude": "48.09140",
          "Longitude": "-122.50482"
        }
      }
    },
    {
      "DataProvider": {
        "Attributes": [
          {
            "Name": "Start time",
            "Value": "07/17 04:14 PM",
            "NoDisplay": false
          },
          {
            "Name": "Customers impacted",
            "Value": "4",
            "NoDisplay": false
          },
          {
            "Name": "Status",
            "Value": "Outage reported",
            "NoDisplay": false
          },
          {
            "Name": "Cause",
            "Value": "Under Investigation",
            "NoDisplay": false
          },
          {
            "Name": "Last update",
            "Value": "07/17 05:40 PM",
            "NoDisplay": false
          },
          {
            "Name": "Est. restoration time",
            "Value": "07/17 06:30 PM",
            "NoDisplay": false
          }
        ],
        "PointOfInterest": {
          "Latitude": "47.52252",
          "Longitude": "-122.18313",
          "MapType": "Outage",
          "PinType": "Outage",
          "Title": "Newcastle",
          "Id": "911432",
          "PlannedOutage": false
        }
      },
      "Polygon": [
        {
          "Latitude": "47.52226",
          "Longitude": "-122.18307"
        },
        {
          "Latitude": "47.52248",
          "Longitude": "-122.18346"
        },
        {
          "Latitude": "47.52255",
          "Longitude": "-122.18346"
        },
        {
          "Latitude": "47.52279",
          "Longitude": "-122.18302"
        },
        {
          "Latitude": "47.52276",
          "Longitude": "-122.18291"
        },
        {
          "Latitude": "47.52256",
          "Longitude": "-122.18290"
        },
        {
          "Latitude": "47.52255",
          "Longitude": "-122.18290"
        },
        {
          "Latitude": "47.52229",
          "Longitude": "-122.18296"
        },
        {
          "Latitude": "47.52226",
          "Longitude": "-122.18307"
        }
      ],
      "BoundingBox": {
        "Min": {
          "Latitude": "47.52226",
          "Longitude": "-122.18346"
        },
        "Max": {
          "Latitude": "47.52279",
          "Longitude": "-122.18290"
        }
      }
    },
    {
      "DataProvider": {
        "Attributes": [
          {
            "Name": "Start time",
            "Value": "07/17 04:27 PM",
            "NoDisplay": false
          },
          {
            "Name": "Customers impacted",
            "Value": "1",
            "NoDisplay": false
          },
          {
            "Name": "Status",
            "Value": "Outage reported",
            "NoDisplay": false
          },
          {
            "Name": "Cause",
            "Value": "Under Investigation",
            "NoDisplay": false
          },
          {
            "Name": "Last update",
            "Value": "07/17 05:40 PM",
            "NoDisplay": false
          },
          {
            "Name": "Est. restoration time",
            "Value": "07/17 06:30 PM",
            "NoDisplay": false
          }
        ],
        "PointOfInterest": {
          "Latitude": "47.71792",
          "Longitude": "-122.18980",
          "MapType": "Outage",
          "PinType": "Outage",
          "Title": "North Juanita",
          "Id": "911435",
          "PlannedOutage": false
        }
      },
      "Polygon": [
        {
          "Latitude": "47.71792",
          "Longitude": "-122.18973"
        },
        {
          "Latitude": "47.71791",
          "Longitude": "-122.18973"
        },
        {
          "Latitude": "47.71790",
          "Longitude": "-122.18973"
        },
        {
          "Latitude": "47.71789",
          "Longitude": "-122.18974"
        },
        {
          "Latitude": "47.71789",
          "Longitude": "-122.18975"
        },
        {
          "Latitude": "47.71788",
          "Longitude": "-122.18976"
        },
        {
          "Latitude": "47.71788",
          "Longitude": "-122.18977"
        },
        {
          "Latitude": "47.71787",
          "Longitude": "-122.18978"
        },
        {
          "Latitude": "47.71787",
          "Longitude": "-122.18980"
        },
        {
          "Latitude": "47.71787",
          "Longitude": "-122.18981"
        },
        {
          "Latitude": "47.71788",
          "Longitude": "-122.18982"
        },
        {
          "Latitude": "47.71788",
          "Longitude": "-122.18983"
        },
        {
          "Latitude": "47.71789",
          "Longitude": "-122.18984"
        },
        {
          "Latitude": "47.71789",
          "Longitude": "-122.18985"
        },
        {
          "Latitude": "47.71790",
          "Longitude": "-122.18986"
        },
        {
          "Latitude": "47.71791",
          "Longitude": "-122.18986"
        },
        {
          "Latitude": "47.71792",
          "Longitude": "-122.18986"
        },
        {
          "Latitude": "47.71793",
          "Longitude": "-122.18986"
        },
        {
          "Latitude": "47.71793",
          "Longitude": "-122.18986"
        },
        {
          "Latitude": "47.71794",
          "Longitude": "-122.18985"
        },
        {
          "Latitude": "47.71795",
          "Longitude": "-122.18984"
        },
        {
          "Latitude": "47.71795",
          "Longitude": "-122.18983"
        },
        {
          "Latitude": "47.71796",
          "Longitude": "-122.18982"
        },
        {
          "Latitude": "47.71796",
          "Longitude": "-122.18981"
        },
        {
          "Latitude": "47.71796",
          "Longitude": "-122.18980"
        },
        {
          "Latitude": "47.71796",
          "Longitude": "-122.18978"
        },
        {
          "Latitude": "47.71796",
          "Longitude": "-122.18977"
        },
        {
          "Latitude": "47.71796",
          "Longitude": "-122.18976"
        },
        {
          "Latitude": "47.71795",
          "Longitude": "-122.18975"
        },
        {
          "Latitude": "47.71794",
          "Longitude": "-122.18974"
        },
        {
          "Latitude": "47.71794",
          "Longitude": "-122.18974"
        },
        {
          "Latitude": "47.71793",
          "Longitude": "-122.18973"
        },
        {
          "Latitude": "47.71792",
          "Longitude": "-122.18973"
        }
      ],
      "BoundingBox": {
        "Min": {
          "Latitude": "47.71787",
          "Longitude": "-122.18986"
        },
        "Max": {
          "Latitude": "47.71796",
          "Longitude": "-122.18973"
        }
      }
    },
    {
      "DataProvider": {
        "Attributes": [
          {
            "Name": "Start time",
            "Value": "07/17 05:14 PM",
            "NoDisplay": false
          },
          {
            "Name": "Customers impacted",
            "Value": "2",
            "NoDisplay": false
          },
          {
            "Name": "Status",
            "Value": "Waiting for repairs",
            "NoDisplay": false
          },
          {
            "Name": "Cause",
            "Value": "Equipment Failure",
            "NoDisplay": false
          },
          {
            "Name": "Last update",
            "Value": "07/17 05:40 PM",
            "NoDisplay": false
          },
          {
            "Name": "Est. restoration time",
            "Value": "07/17 07:30 PM",
            "NoDisplay": false
          }
        ],
        "PointOfInterest": {
          "Latitude": "46.97975",
          "Longitude": "-122.84206",
          "MapType": "Outage",
          "PinType": "Outage",
          "Title": "Olympia",
          "Id": "911446",
          "PlannedOutage": false
        }
      },
      "Polygon": [
        {
          "Latitude": "46.97990",
          "Longitude": "-122.84239"
        },
        {
          "Latitude": "46.97991",
          "Longitude": "-122.84239"
        },
        {
          "Latitude": "46.97992",
          "Longitude": "-122.84240"
        },
        {
          "Latitude": "46.97992",
          "Longitude": "-122.84241"
        },
        {
          "Latitude": "46.97993",
          "Longitude": "-122.84241"
        },
        {
          "Latitude": "46.97994",
          "Longitude": "-122.84241"
        },
        {
          "Latitude": "46.97995",
          "Longitude": "-122.84240"
        },
        {
          "Latitude": "46.97996",
          "Longitude": "-122.84240"
        },
        {
          "Latitude": "46.97996",
          "Longitude": "-122.84239"
        },
        {
          "Latitude": "46.97997",
          "Longitude": "-122.84238"
        },
        {
          "Latitude": "46.97997",
          "Longitude": "-122.84237"
        },
        {
          "Latitude": "46.97998",
          "Longitude": "-122.84236"
        },
        {
          "Latitude": "46.97998",
          "Longitude": "-122.84234"
        },
        {
          "Latitude": "46.97998",
          "Longitude": "-122.84233"
        },
        {
          "Latitude": "46.97998",
          "Longitude": "-122.84232"
        },
        {
          "Latitude": "46.97997",
          "Longitude": "-122.84231"
        },
        {
          "Latitude": "46.97997",
          "Longitude": "-122.84230"
        },
        {
          "Latitude": "46.97961",
          "Longitude": "-122.84174"
        },
        {
          "Latitude": "46.97960",
          "Longitude": "-122.84173"
        },
        {
          "Latitude": "46.97959",
          "Longitude": "-122.84172"
        },
        {
          "Latitude": "46.97958",
          "Longitude": "-122.84172"
        },
        {
          "Latitude": "46.97957",
          "Longitude": "-122.84172"
        },
        {
          "Latitude": "46.97957",
          "Longitude": "-122.84172"
        },
        {
          "Latitude": "46.97956",
          "Longitude": "-122.84172"
        },
        {
          "Latitude": "46.97955",
          "Longitude": "-122.84173"
        },
        {
          "Latitude": "46.97954",
          "Longitude": "-122.84173"
        },
        {
          "Latitude": "46.97954",
          "Longitude": "-122.84174"
        },
        {
          "Latitude": "46.97953",
          "Longitude": "-122.84175"
        },
        {
          "Latitude": "46.97953",
          "Longitude": "-122.84177"
        },
        {
          "Latitude": "46.97953",
          "Longitude": "-122.84178"
        },
        {
          "Latitude": "46.97953",
          "Longitude": "-122.84179"
        },
        {
          "Latitude": "46.97953",
          "Longitude": "-122.84180"
        },
        {
          "Latitude": "46.97953",
          "Longitude": "-122.84182"
        },
        {
          "Latitude": "46.97954",
          "Longitude": "-122.84183"
        },
        {
          "Latitude": "46.97990",
          "Longitude": "-122.84239"
        }
      ],
      "BoundingBox": {
        "Min": {
          "Latitude": "46.97953",
          "Longitude": "-122.84241"
        },
        "Max": {
          "Latitude": "46.97998",
          "Longitude": "-122.84172"
        }
      }
    },
    {
      "DataProvider": {
        "Attributes": [
          {
            "Name": "Start time",
            "Value": "07/17 05:08 PM",
            "NoDisplay": false
          },
          {
            "Name": "Customers impacted",
            "Value": "1",
            "NoDisplay": false
          },
          {
            "Name": "Status",
            "Value": "Outage reported",
            "NoDisplay": false
          },
          {
            "Name": "Cause",
            "Value": "Under Investigation",
            "NoDisplay": false
          },
          {
            "Name": "Last update",
            "Value": "07/17 05:40 PM",
            "NoDisplay": false
          },
          {
            "Name": "Est. restoration time",
            "Value": "07/17 07:30 PM",
            "NoDisplay": false
          }
        ],
        "PointOfInterest": {
          "Latitude": "47.51193",
          "Longitude": "-122.70367",
          "MapType": "Outage",
          "PinType": "Outage",
          "Title": "Port Orchard",
          "Id": "911444",
          "PlannedOutage": false
        }
      },
      "Polygon": [
        {
          "Latitude": "47.51192",
          "Longitude": "-122.70361"
        },
        {
          "Latitude": "47.51192",
          "Longitude": "-122.70361"
        },
        {
          "Latitude": "47.51191",
          "Longitude": "-122.70361"
        },
        {
          "Latitude": "47.51190",
          "Longitude": "-122.70362"
        },
        {
          "Latitude": "47.51189",
          "Longitude": "-122.70363"
        },
        {
          "Latitude": "47.51189",
          "Longitude": "-122.70364"
        },
        {
          "Latitude": "47.51188",
          "Longitude": "-122.70365"
        },
        {
          "Latitude": "47.51188",
          "Longitude": "-122.70366"
        },
        {
          "Latitude": "47.51188",
          "Longitude": "-122.70367"
        },
        {
          "Latitude": "47.51188",
          "Longitude": "-122.70369"
        },
        {
          "Latitude": "47.51188",
          "Longitude": "-122.70370"
        },
        {
          "Latitude": "47.51189",
          "Longitude": "-122.70371"
        },
        {
          "Latitude": "47.51189",
          "Longitude": "-122.70372"
        },
        {
          "Latitude": "47.51190",
          "Longitude": "-122.70373"
        },
        {
          "Latitude": "47.51191",
          "Longitude": "-122.70374"
        },
        {
          "Latitude": "47.51191",
          "Longitude": "-122.70374"
        },
        {
          "Latitude": "47.51192",
          "Longitude": "-122.70374"
        },
        {
          "Latitude": "47.51193",
          "Longitude": "-122.70374"
        },
        {
          "Latitude": "47.51194",
          "Longitude": "-122.70374"
        },
        {
          "Latitude": "47.51195",
          "Longitude": "-122.70373"
        },
        {
          "Latitude": "47.51195",
          "Longitude": "-122.70372"
        },
        {
          "Latitude": "47.51196",
          "Longitude": "-122.70371"
        },
        {
          "Latitude": "47.51196",
          "Longitude": "-122.70370"
        },
        {
          "Latitude": "47.51197",
          "Longitude": "-122.70369"
        },
        {
          "Latitude": "47.51197",
          "Longitude": "-122.70368"
        },
        {
          "Latitude": "47.51197",
          "Longitude": "-122.70366"
        },
        {
          "Latitude": "47.51197",
          "Longitude": "-122.70365"
        },
        {
          "Latitude": "47.51196",
          "Longitude": "-122.70364"
        },
        {
          "Latitude": "47.51196",
          "Longitude": "-122.70363"
        },
        {
          "Latitude": "47.51195",
          "Longitude": "-122.70362"
        },
        {
          "Latitude": "47.51194",
          "Longitude": "-122.70361"
        },
        {
          "Latitude": "47.51193",
          "Longitude": "-122.70361"
        },
        {
          "Latitude": "47.51192",
          "Longitude": "-122.70361"
        }
      ],
      "BoundingBox": {
        "Min": {
          "Latitude": "47.51188",
          "Longitude": "-122.70374"
        },
        "Max": {
          "Latitude": "47.51197",
          "Longitude": "-122.70361"
        }
      }
    },
    {
      "DataProvider": {
        "Attributes": [
          {
            "Name": "Start time",
            "Value": "07/17 11:43 AM",
            "NoDisplay": false
          },
          {
            "Name": "Customers impacted",
            "Value": "63",
            "NoDisplay": false
          },
          {
            "Name": "Status",
            "Value": "Repair crew onsite",
            "NoDisplay": false
          },
          {
            "Name": "Cause",
            "Value": "Trees/Vegetation",
            "NoDisplay": false
          },
          {
            "Name": "Last update",
            "Value": "07/17 05:40 PM",
            "NoDisplay": false
          },
          {
            "Name": "Est. restoration time",
            "Value": "07/18 01:00 AM",
            "NoDisplay": false
          }
        ],
        "PointOfInterest": {
          "Latitude": "47.85473",
          "Longitude": "-122.58683",
          "MapType": "Outage",
          "PinType": "Outage",
          "Title": "Poulsbo",
          "Id": "911356",
          "PlannedOutage": false
        }
      },
      "Polygon": [
        {
          "Latitude": "47.85213",
          "Longitude": "-122.58461"
        },
        {
          "Latitude": "47.85323",
          "Longitude": "-122.58979"
        },
        {
          "Latitude": "47.85324",
          "Longitude": "-122.58980"
        },
        {
          "Latitude": "47.85335",
          "Longitude": "-122.59006"
        },
        {
          "Latitude": "47.85336",
          "Longitude": "-122.59008"
        },
        {
          "Latitude": "47.85593",
          "Longitude": "-122.59257"
        },
        {
          "Latitude": "47.85598",
          "Longitude": "-122.59257"
        },
        {
          "Latitude": "47.85610",
          "Longitude": "-122.59246"
        },
        {
          "Latitude": "47.85612",
          "Longitude": "-122.59242"
        },
        {
          "Latitude": "47.85665",
          "Longitude": "-122.58757"
        },
        {
          "Latitude": "47.85665",
          "Longitude": "-122.58755"
        },
        {
          "Latitude": "47.85642",
          "Longitude": "-122.58255"
        },
        {
          "Latitude": "47.85638",
          "Longitude": "-122.58249"
        },
        {
          "Latitude": "47.85517",
          "Longitude": "-122.58216"
        },
        {
          "Latitude": "47.85516",
          "Longitude": "-122.58216"
        },
        {
          "Latitude": "47.85512",
          "Longitude": "-122.58217"
        },
        {
          "Latitude": "47.85511",
          "Longitude": "-122.58217"
        },
        {
          "Latitude": "47.85423",
          "Longitude": "-122.58250"
        },
        {
          "Latitude": "47.85421",
          "Longitude": "-122.58251"
        },
        {
          "Latitude": "47.85215",
          "Longitude": "-122.58453"
        },
        {
          "Latitude": "47.85213",
          "Longitude": "-122.58461"
        }
      ],
      "BoundingBox": {
        "Min": {
          "Latitude": "47.85213",
          "Longitude": "-122.59257"
        },
        "Max": {
          "Latitude": "47.85665",
          "Longitude": "-122.58216"
        }
      }
    },
    {
      "DataProvider": {
        "Attributes": [
          {
            "Name": "Start time",
            "Value": "07/15 07:24 PM",
            "NoDisplay": false
          },
          {
            "Name": "Customers impacted",
            "Value": "4",
            "NoDisplay": false
          },
          {
            "Name": "Status",
            "Value": "Outage reported",
            "NoDisplay": false
          },
          {
            "Name": "Cause",
            "Value": "Under Investigation",
            "NoDisplay": false
          },
          {
            "Name": "Last update",
            "Value": "07/17 05:40 PM",
            "NoDisplay": false
          },
          {
            "Name": "Est. restoration time",
            "Value": "07/22 09:30 PM",
            "NoDisplay": false
          }
        ],
        "PointOfInterest": {
          "Latitude": "47.69191",
          "Longitude": "-121.33733",
          "MapType": "Outage",
          "PinType": "Outage",
          "Title": "Skykomish",
          "Id": "911028",
          "PlannedOutage": false
        }
      },
      "Polygon": [
        {
          "Latitude": "47.68689",
          "Longitude": "-121.33666"
        },
        {
          "Latitude": "47.69441",
          "Longitude": "-121.33782"
        },
        {
          "Latitude": "47.69446",
          "Longitude": "-121.33776"
        },
        {
          "Latitude": "47.69446",
          "Longitude": "-121.33763"
        },
        {
          "Latitude": "47.69442",
          "Longitude": "-121.33756"
        },
        {
          "Latitude": "47.68690",
          "Longitude": "-121.33653"
        },
        {
          "Latitude": "47.68689",
          "Longitude": "-121.33666"
        }
      ],
      "BoundingBox": {
        "Min": {
          "Latitude": "47.68689",
          "Longitude": "-121.33782"
        },
        "Max": {
          "Latitude": "47.69446",
          "Longitude": "-121.33653"
        }
      }
    },
    {
      "DataProvider": {
        "Attributes": [
          {
            "Name": "Start time",
            "Value": "07/17 05:16 PM",
            "NoDisplay": false
          },
          {
            "Name": "Customers impacted",
            "Value": "606",
            "NoDisplay": false
          },
          {
            "Name": "Status",
            "Value": "Waiting for repairs",
            "NoDisplay": false
          },
          {
            "Name": "Cause",
            "Value": "Under Investigation",
            "NoDisplay": false
          },
          {
            "Name": "Last update",
            "Value": "07/17 05:40 PM",
            "NoDisplay": false
          },
          {
            "Name": "Est. restoration time",
            "Value": "07/17 07:30 PM",
            "NoDisplay": false
          }
        ],
        "PointOfInterest": {
          "Latitude": "47.45289",
          "Longitude": "-122.49442",
          "MapType": "Outage",
          "PinType": "Outage",
          "Title": "Vashon",
          "Id": "911447",
          "PlannedOutage": false
        }
      },
      "Polygon": [
        {
          "Latitude": "47.42498",
          "Longitude": "-122.51053"
        },
        {
          "Latitude": "47.42552",
          "Longitude": "-122.51169"
        },
        {
          "Latitude": "47.42555",
          "Longitude": "-122.51172"
        },
        {
          "Latitude": "47.42715",
          "Longitude": "-122.51201"
        },
        {
          "Latitude": "47.42715",
          "Longitude": "-122.51201"
        },
        {
          "Latitude": "47.43870",
          "Longitude": "-122.51338"
        },
        {
          "Latitude": "47.43871",
          "Longitude": "-122.51338"
        },
        {
          "Latitude": "47.44836",
          "Longitude": "-122.51352"
        },
        {
          "Latitude": "47.44837",
          "Longitude": "-122.51352"
        },
        {
          "Latitude": "47.45441",
          "Longitude": "-122.51178"
        },
        {
          "Latitude": "47.45442",
          "Longitude": "-122.51178"
        },
        {
          "Latitude": "47.47567",
          "Longitude": "-122.49638"
        },
        {
          "Latitude": "47.47568",
          "Longitude": "-122.49637"
        },
        {
          "Latitude": "47.47760",
          "Longitude": "-122.49384"
        },
        {
          "Latitude": "47.47762",
          "Longitude": "-122.49382"
        },
        {
          "Latitude": "47.47807",
          "Longitude": "-122.49236"
        },
        {
          "Latitude": "47.47807",
          "Longitude": "-122.49236"
        },
        {
          "Latitude": "47.47819",
          "Longitude": "-122.49188"
        },
        {
          "Latitude": "47.47819",
          "Longitude": "-122.49188"
        },
        {
          "Latitude": "47.47916",
          "Longitude": "-122.48778"
        },
        {
          "Latitude": "47.47916",
          "Longitude": "-122.48777"
        },
        {
          "Latitude": "47.47968",
          "Longitude": "-122.48438"
        },
        {
          "Latitude": "47.47966",
          "Longitude": "-122.48431"
        },
        {
          "Latitude": "47.47832",
          "Longitude": "-122.48274"
        },
        {
          "Latitude": "47.47831",
          "Longitude": "-122.48273"
        },
        {
          "Latitude": "47.46436",
          "Longitude": "-122.47399"
        },
        {
          "Latitude": "47.46435",
          "Longitude": "-122.47398"
        },
        {
          "Latitude": "47.46096",
          "Longitude": "-122.47241"
        },
        {
          "Latitude": "47.46094",
          "Longitude": "-122.47241"
        },
        {
          "Latitude": "47.45429",
          "Longitude": "-122.47204"
        },
        {
          "Latitude": "47.45427",
          "Longitude": "-122.47205"
        },
        {
          "Latitude": "47.42723",
          "Longitude": "-122.50058"
        },
        {
          "Latitude": "47.42723",
          "Longitude": "-122.50059"
        },
        {
          "Latitude": "47.42570",
          "Longitude": "-122.50252"
        },
        {
          "Latitude": "47.42569",
          "Longitude": "-122.50256"
        },
        {
          "Latitude": "47.42497",
          "Longitude": "-122.51048"
        },
        {
          "Latitude": "47.42498",
          "Longitude": "-122.51053"
        }
      ],
      "BoundingBox": {
        "Min": {
          "Latitude": "47.42497",
          "Longitude": "-122.51352"
        },
        "Max": {
          "Latitude": "47.47968",
          "Longitude": "-122.47204"
        }
      }
    },
    {
      "DataProvider": {
        "Attributes": [
          {
            "Name": "Start time",
            "Value": "07/17 05:29 PM",
            "NoDisplay": false
          },
          {
            "Name": "Customers impacted",
            "Value": "7",
            "NoDisplay": false
          },
          {
            "Name": "Status",
            "Value": "Outage reported",
            "NoDisplay": false
          },
          {
            "Name": "Cause",
            "Value": "Under Investigation",
            "NoDisplay": false
          },
          {
            "Name": "Last update",
            "Value": "07/17 05:40 PM",
            "NoDisplay": false
          },
          {
            "Name": "Est. restoration time",
            "Value": "07/17 07:30 PM",
            "NoDisplay": false
          }
        ],
        "PointOfInterest": {
          "Latitude": "47.68141",
          "Longitude": "-122.16207",
          "MapType": "Outage",
          "PinType": "Outage",
          "Title": "Willow - Rose Hill",
          "Id": "911459",
          "PlannedOutage": false
        }
      },
      "Polygon": [
        {
          "Latitude": "47.68114",
          "Longitude": "-122.16236"
        },
        {
          "Latitude": "47.68129",
          "Longitude": "-122.16225"
        },
        {
          "Latitude": "47.68129",
          "Longitude": "-122.16225"
        },
        {
          "Latitude": "47.68157",
          "Longitude": "-122.16203"
        },
        {
          "Latitude": "47.68158",
          "Longitude": "-122.16202"
        },
        {
          "Latitude": "47.68162",
          "Longitude": "-122.16196"
        },
        {
          "Latitude": "47.68157",
          "Longitude": "-122.16185"
        },
        {
          "Latitude": "47.68109",
          "Longitude": "-122.16225"
        },
        {
          "Latitude": "47.68114",
          "Longitude": "-122.16236"
        }
      ],
      "BoundingBox": {
        "Min": {
          "Latitude": "47.68109",
          "Longitude": "-122.16236"
        },
        "Max": {
          "Latitude": "47.68162",
          "Longitude": "-122.16185"
        }
      }
    }
  ],
  "LastUpdated": "2023-07-18T00:44:11+00:00"
}
