{
  "UnplannedOutageSummary": {
    "CustomerAfftectedCount": 15,
    "OutageCount": 8,
    "LastUpdatedDatetime": "04/07 03:19 PM"
  },
  "PlannedOutageSummary": {
    "CustomerAfftectedCount": 13,
    "OutageCount": 4,
    "LastUpdatedDatetime": "04/07 03:19 PM"
  },
  "PSPSSummary": {
    "CustomerAfftectedCount": 0,
    "OutageCount": 0,
    "LastUpdatedDatetime": "04/07 03:19 PM"
  },
  "CustomerProfile": null,
  "PseMap": [
    {
      "DataProvider": {
        "Attributes": [
          {
            "Name": "Start time",
            "RefName": "StartDate",
            "Value": "04/07 11:29 AM",
            "RefValue": "",
            "NoDisplay": false
          },
          {
            "Name": "Customers impacted",
            "RefName": "Customers impacted",
            "Value": "3",
            "RefValue": "",
            "NoDisplay": false
          },
          {
            "Name": "Status",
            "RefName": "Status",
            "Value": "Crew onsite",
            "RefValue": "Repair crew onsite",
            "NoDisplay": false
          },
          {
            "Name": "Cause",
            "RefName": "Cause",
            "Value": "Dig up underground",
            "RefValue": "",
            "NoDisplay": false
          },
          {
            "Name": "Last update",
            "RefName": "LastUpdated",
            "Value": "04/07 03:15 PM",
            "RefValue": "",
            "NoDisplay": false
          },
          {
            "Name": "Est. restoration time",
            "RefName": "Est. Restoration time",
            "Value": "04/07 06:00 PM",
            "RefValue": "",
            "NoDisplay": false
          },
          {
            "Name": "Outage ID",
            "RefName": "OutageEventId",
            "Value": "INC1140118227",
            "RefValue": "",
            "NoDisplay": false
          }
        ],
        "PointOfInterest": {
          "Latitude": "48.44719",
          "Longitude": "-122.63429",
          "MapType": "Outage",
          "PinType": "Outage",
          "OrderType": "Outage",
          "Title": "Anacortes",
          "Id": "INC1140118227",
          "PlannedOutage": false,
          "FilterType": "Outage",
          "IsHve": false
        },
        "CRCAttributes": null
      },
      "Polygon": [
        {
          "Latitude": "48.44697",
          "Longitude": "-122.63436"
        },
        {
          "Latitude": "48.44696",
          "Longitude": "-122.63437"
        },
        {
          "Latitude": "48.44696",
          "Longitude": "-122.63438"
        },
        {
          "Latitude": "48.44695",
          "Longitude": "-122.63439"
        },
        {
          "Latitude": "48.44695",
          "Longitude": "-122.63440"
        },
        {
          "Latitude": "48.44695",
          "Longitude": "-122.63441"
        },
        {
          "Latitude": "48.44695",
          "Longitude": "-122.63443"
        },
        {
          "Latitude": "48.44695",
          "Longitude": "-122.63444"
        },
        {
          "Latitude": "48.44695",
          "Longitude": "-122.63445"
        },
        {
          "Latitude": "48.44695",
          "Longitude": "-122.63446"
        },
        {
          "Latitude": "48.44696",
          "Longitude": "-122.63447"
        },
        {
          "Latitude": "48.44697",
          "Longitude": "-122.63448"
        },
        {
          "Latitude": "48.44698",
          "Longitude": "-122.63449"
        },
        {
          "Latitude": "48.44698",
          "Longitude": "-122.63449"
        },
        {
          "Latitude": "48.44699",
          "Longitude": "-122.63449"
        },
        {
          "Latitude": "48.44700",
          "Longitude": "-122.63449"
        },
        {
          "Latitude": "48.44701",
          "Longitude": "-122.63448"
        },
        {
          "Latitude": "48.44740",
          "Longitude": "-122.63421"
        },
        {
          "Latitude": "48.44741",
          "Longitude": "-122.63420"
        },
        {
          "Latitude": "48.44742",
          "Longitude": "-122.63419"
        },
        {
          "Latitude": "48.44742",
          "Longitude": "-122.63418"
        },
        {
          "Latitude": "48.44743",
          "Longitude": "-122.63417"
        },
        {
          "Latitude": "48.44743",
          "Longitude": "-122.63416"
        },
        {
          "Latitude": "48.44743",
          "Longitude": "-122.63414"
        },
        {
          "Latitude": "48.44743",
          "Longitude": "-122.63413"
        },
        {
          "Latitude": "48.44742",
          "Longitude": "-122.63412"
        },
        {
          "Latitude": "48.44742",
          "Longitude": "-122.63411"
        },
        {
          "Latitude": "48.44741",
          "Longitude": "-122.63410"
        },
        {
          "Latitude": "48.44741",
          "Longitude": "-122.63409"
        },
        {
          "Latitude": "48.44740",
          "Longitude": "-122.63408"
        },
        {
          "Latitude": "48.44739",
          "Longitude": "-122.63408"
        },
        {
          "Latitude": "48.44738",
          "Longitude": "-122.63408"
        },
        {
          "Latitude": "48.44737",
          "Longitude": "-122.63408"
        },
        {
          "Latitude": "48.44736",
          "Longitude": "-122.63409"
        },
        {
          "Latitude": "48.44697",
          "Longitude": "-122.63436"
        }
      ],
      "BoundingBox": {
        "Min": {
          "Latitude": "48.44695",
          "Longitude": "-122.63449"
        },
        "Max": {
          "Latitude": "48.44743",
          "Longitude": "-122.63408"
        }
      }
    },
    {
      "DataProvider": {
        "Attributes": [
          {
            "Name": "Start time",
            "RefName": "StartDate",
            "Value": "04/07 09:32 AM",
            "RefValue": "",
            "NoDisplay": false
          },
          {
            "Name": "Customers impacted",
            "RefName": "Customers impacted",
            "Value": "5",
            "RefValue": "",
            "NoDisplay": false
          },
          {
            "Name": "Status",
            "RefName": "Status",
            "Value": "Crew onsite",
            "RefValue": "Repair crew onsite",
            "NoDisplay": false
          },
          {
            "Name": "Cause",
            "RefName": "Cause",
            "Value": "Under investigation",
            "RefValue": "",
            "NoDisplay": false
          },
          {
            "Name": "Last update",
            "RefName": "LastUpdated",
            "Value": "04/07 03:15 PM",
            "RefValue": "",
            "NoDisplay": false
          },
          {
            "Name": "Est. restoration time",
            "RefName": "Est. Restoration time",
            "Value": "04/07 01:00 PM",
            "RefValue": "",
            "NoDisplay": false
          },
          {
            "Name": "Outage ID",
            "RefName": "OutageEventId",
            "Value": "INC1140118186",
            "RefValue": "",
            "NoDisplay": false
          }
        ],
        "PointOfInterest": {
          "Latitude": "47.25256",
          "Longitude": "-122.11420",
          "MapType": "Outage",
          "PinType": "Outage",
          "OrderType": "Switching",
          "Title": "Auburn",
          "Id": "INC1140118186",
          "PlannedOutage": true,
          "FilterType": "Planned",
          "IsHve": false
        },
        "CRCAttributes": null
      },
      "Polygon": [
        {
          "Latitude": "47.25233",
          "Longitude": "-122.11375"
        },
        {
          "Latitude": "47.25252",
          "Longitude": "-122.11545"
        },
        {
          "Latitude": "47.25260",
          "Longitude": "-122.11547"
        },
        {
          "Latitude": "47.25280",
          "Longitude": "-122.11492"
        },
        {
          "Latitude": "47.25281",
          "Longitude": "-122.11488"
        },
        {
          "Latitude": "47.25255",
          "Longitude": "-122.11271"
        },
        {
          "Latitude": "47.25246",
          "Longitude": "-122.11271"
        },
        {
          "Latitude": "47.25233",
          "Longitude": "-122.11373"
        },
        {
          "Latitude": "47.25233",
          "Longitude": "-122.11375"
        }
      ],
      "BoundingBox": {
        "Min": {
          "Latitude": "47.25233",
          "Longitude": "-122.11547"
        },
        "Max": {
          "Latitude": "47.25281",
          "Longitude": "-122.11271"
        }
      }
    },
    {
      "DataProvider": {
        "Attributes": [
          {
            "Name": "Start time",
            "RefName": "StartDate",
            "Value": "04/07 02:21 PM",
            "RefValue": "",
            "NoDisplay": false
          },
          {
            "Name": "Customers impacted",
            "RefName": "Customers impacted",
            "Value": "1",
            "RefValue": "",
            "NoDisplay": false
          },
          {
            "Name": "Status",
            "RefName": "Status",
            "Value": "Assessing damage",
            "RefValue": "Waiting for repairs",
            "NoDisplay": false
          },
          {
            "Name": "Cause",
            "RefName": "Cause",
            "Value": "Under investigation",
            "RefValue": "",
            "NoDisplay": false
          },
          {
            "Name": "Last update",
            "RefName": "LastUpdated",
            "Value": "04/07 03:15 PM",
            "RefValue": "",
            "NoDisplay": false
          },
          {
            "Name": "Est. restoration time",
            "RefName": "Est. Restoration time",
            "Value": "04/07 05:30 PM",
            "RefValue": "",
            "NoDisplay": false
          },
          {
            "Name": "Outage ID",
            "RefName": "OutageEventId",
            "Value": "INC1140118602",
            "RefValue": "",
            "NoDisplay": false
          }
        ],
        "PointOfInterest": {
          "Latitude": "47.31964",
          "Longitude": "-122.17150",
          "MapType": "Outage",
          "PinType": "Outage",
          "OrderType": "Outage",
          "Title": "Auburn",
          "Id": "INC1140118602",
          "PlannedOutage": false,
          "FilterType": "Outage",
          "IsHve": false
        },
        "CRCAttributes": null
      },
      "Polygon": [
        {
          "Latitude": "47.31964",
          "Longitude": "-122.17144"
        },
        {
          "Latitude": "47.31963",
          "Longitude": "-122.17144"
        },
        {
          "Latitude": "47.31962",
          "Longitude": "-122.17144"
        },
        {
          "Latitude": "47.31962",
          "Longitude": "-122.17145"
        },
        {
          "Latitude": "47.31961",
          "Longitude": "-122.17145"
        },
        {
          "Latitude": "47.31960",
          "Longitude": "-122.17146"
        },
        {
          "Latitude": "47.31960",
          "Longitude": "-122.17147"
        },
        {
          "Latitude": "47.31960",
          "Longitude": "-122.17149"
        },
        {
          "Latitude": "47.31960",
          "Longitude": "-122.17150"
        },
        {
          "Latitude": "47.31960",
          "Longitude": "-122.17151"
        },
        {
          "Latitude": "47.31960",
          "Longitude": "-122.17153"
        },
        {
          "Latitude": "47.31960",
          "Longitude": "-122.17154"
        },
        {
          "Latitude": "47.31961",
          "Longitude": "-122.17155"
        },
        {
          "Latitude": "47.31962",
          "Longitude": "-122.17156"
        },
        {
          "Latitude": "47.31962",
          "Longitude": "-122.17156"
        },
        {
          "Latitude": "47.31963",
          "Longitude": "-122.17157"
        },
        {
          "Latitude": "47.31964",
          "Longitude": "-122.17157"
        },
        {
          "Latitude": "47.31965",
          "Longitude": "-122.17157"
        },
        {
          "Latitude": "47.31966",
          "Longitude": "-122.17156"
        },
        {
          "Latitude": "47.31967",
          "Longitude": "-122.17156"
        },
        {
          "Latitude": "47.31967",
          "Longitude": "-122.17155"
        },
        {
          "Latitude": "47.31968",
          "Longitude": "-122.17154"
        },
        {
          "Latitude": "47.31968",
          "Longitude": "-122.17153"
        },
        {
          "Latitude": "47.31969",
          "Longitude": "-122.17152"
        },
        {
          "Latitude": "47.31969",
          "Longitude": "-122.17150"
        },
        {
          "Latitude": "47.31969",
          "Longitude": "-122.17149"
        },
        {
          "Latitude": "47.31968",
          "Longitude": "-122.17148"
        },
        {
          "Latitude": "47.31968",
          "Longitude": "-122.17147"
        },
        {
          "Latitude": "47.31967",
          "Longitude": "-122.17146"
        },
        {
          "Latitude": "47.31967",
          "Longitude": "-122.17145"
        },
        {
          "Latitude": "47.31966",
          "Longitude": "-122.17144"
        },
        {
          "Latitude": "47.31965",
          "Longitude": "-122.17144"
        },
        {
          "Latitude": "47.31964",
          "Longitude": "-122.17144"
        }
      ],
      "BoundingBox": {
        "Min": {
          "Latitude": "47.31960",
          "Longitude": "-122.17157"
        },
        "Max": {
          "Latitude": "47.31969",
          "Longitude": "-122.17144"
        }
      }
    },
    {
      "DataProvider": {
        "Attributes": [
          {
            "Name": "Start time",
            "RefName": "StartDate",
            "Value": "04/07 10:58 AM",
            "RefValue": "",
            "NoDisplay": false
          },
          {
            "Name": "Customers impacted",
            "RefName": "Customers impacted",
            "Value": "2",
            "RefValue": "",
            "NoDisplay": false
          },
          {
            "Name": "Status",
            "RefName": "Status",
            "Value": "Crew onsite",
            "RefValue": "Repair crew onsite",
            "NoDisplay": false
          },
          {
            "Name": "Cause",
            "RefName": "Cause",
            "Value": "Scheduled outage",
            "RefValue": "",
            "NoDisplay": false
          },
          {
            "Name": "Last update",
            "RefName": "LastUpdated",
            "Value": "04/07 03:15 PM",
            "RefValue": "",
            "NoDisplay": false
          },
          {
            "Name": "Est. restoration time",
            "RefName": "Est. Restoration time",
            "Value": "04/07 02:00 PM",
            "RefValue": "",
            "NoDisplay": false
          },
          {
            "Name": "Outage ID",
            "RefName": "OutageEventId",
            "Value": "INC1140118218",
            "RefValue": "",
            "NoDisplay": false
          }
        ],
        "PointOfInterest": {
          "Latitude": "47.56664",
          "Longitude": "-122.70061",
          "MapType": "Outage",
          "PinType": "Outage",
          "OrderType": "Switching",
          "Title": "Bremerton",
          "Id": "INC1140118218",
          "PlannedOutage": true,
          "FilterType": "Planned",
          "IsHve": false
        },
        "CRCAttributes": null
      },
      "Polygon": [
        {
          "Latitude": "47.56675",
          "Longitude": "-122.70063"
        },
        {
          "Latitude": "47.56676",
          "Longitude": "-122.70062"
        },
        {
          "Latitude": "47.56676",
          "Longitude": "-122.70061"
        },
        {
          "Latitude": "47.56677",
          "Longitude": "-122.70060"
        },
        {
          "Latitude": "47.56677",
          "Longitude": "-122.70059"
        },
        {
          "Latitude": "47.56678",
          "Longitude": "-122.70058"
        },
        {
          "Latitude": "47.56678",
          "Longitude": "-122.70057"
        },
        {
          "Latitude": "47.56678",
          "Longitude": "-122.70055"
        },
        {
          "Latitude": "47.56678",
          "Longitude": "-122.70054"
        },
        {
          "Latitude": "47.56677",
          "Longitude": "-122.70053"
        },
        {
          "Latitude": "47.56677",
          "Longitude": "-122.70052"
        },
        {
          "Latitude": "47.56676",
          "Longitude": "-122.70051"
        },
        {
          "Latitude": "47.56676",
          "Longitude": "-122.70050"
        },
        {
          "Latitude": "47.56675",
          "Longitude": "-122.70050"
        },
        {
          "Latitude": "47.56674",
          "Longitude": "-122.70050"
        },
        {
          "Latitude": "47.56673",
          "Longitude": "-122.70050"
        },
        {
          "Latitude": "47.56672",
          "Longitude": "-122.70050"
        },
        {
          "Latitude": "47.56653",
          "Longitude": "-122.70058"
        },
        {
          "Latitude": "47.56653",
          "Longitude": "-122.70059"
        },
        {
          "Latitude": "47.56652",
          "Longitude": "-122.70059"
        },
        {
          "Latitude": "47.56651",
          "Longitude": "-122.70060"
        },
        {
          "Latitude": "47.56651",
          "Longitude": "-122.70061"
        },
        {
          "Latitude": "47.56650",
          "Longitude": "-122.70063"
        },
        {
          "Latitude": "47.56650",
          "Longitude": "-122.70064"
        },
        {
          "Latitude": "47.56650",
          "Longitude": "-122.70065"
        },
        {
          "Latitude": "47.56650",
          "Longitude": "-122.70066"
        },
        {
          "Latitude": "47.56651",
          "Longitude": "-122.70068"
        },
        {
          "Latitude": "47.56651",
          "Longitude": "-122.70069"
        },
        {
          "Latitude": "47.56652",
          "Longitude": "-122.70070"
        },
        {
          "Latitude": "47.56653",
          "Longitude": "-122.70070"
        },
        {
          "Latitude": "47.56653",
          "Longitude": "-122.70071"
        },
        {
          "Latitude": "47.56654",
          "Longitude": "-122.70071"
        },
        {
          "Latitude": "47.56655",
          "Longitude": "-122.70071"
        },
        {
          "Latitude": "47.56656",
          "Longitude": "-122.70071"
        },
        {
          "Latitude": "47.56675",
          "Longitude": "-122.70063"
        }
      ],
      "BoundingBox": {
        "Min": {
          "Latitude": "47.56650",
          "Longitude": "-122.70071"
        },
        "Max": {
          "Latitude": "47.56678",
          "Longitude": "-122.70050"
        }
      }
    },
    {
      "DataProvider": {
        "Attributes": [
          {
            "Name": "Start time",
            "RefName": "StartDate",
            "Value": "04/07 12:25 PM",
            "RefValue": "",
            "NoDisplay": false
          },
          {
            "Name": "Customers impacted",
            "RefName": "Customers impacted",
            "Value": "1",
            "RefValue": "",
            "NoDisplay": false
          },
          {
            "Name": "Status",
            "RefName": "Status",
            "Value": "Outage reported",
            "RefValue": "Outage reported",
            "NoDisplay": false
          },
          {
            "Name": "Cause",
            "RefName": "Cause",
            "Value": "Accident",
            "RefValue": "",
            "NoDisplay": false
          },
          {
            "Name": "Last update",
            "RefName": "LastUpdated",
            "Value": "04/07 03:15 PM",
            "RefValue": "",
            "NoDisplay": false
          },
          {
            "Name": "Est. restoration time",
            "RefName": "Est. Restoration time",
            "Value": "04/07 05:30 PM",
            "RefValue": "",
            "NoDisplay": false
          },
          {
            "Name": "Outage ID",
            "RefName": "OutageEventId",
            "Value": "INC1140118244",
            "RefValue": "",
            "NoDisplay": false
          }
        ],
        "PointOfInterest": {
          "Latitude": "47.58401",
          "Longitude": "-122.69415",
          "MapType": "Outage",
          "PinType": "Outage",
          "OrderType": "Crew1 - Outage",
          "Title": "Bremerton",
          "Id": "INC1140118244",
          "PlannedOutage": false,
          "FilterType": "Outage",
          "IsHve": false
        },
        "CRCAttributes": null
      },
      "Polygon": [
        {
          "Latitude": "47.58401",
          "Longitude": "-122.69409"
        },
        {
          "Latitude": "47.58400",
          "Longitude": "-122.69409"
        },
        {
          "Latitude": "47.58399",
          "Longitude": "-122.69409"
        },
        {
          "Latitude": "47.58399",
          "Longitude": "-122.69410"
        },
        {
          "Latitude": "47.58398",
          "Longitude": "-122.69410"
        },
        {
          "Latitude": "47.58397",
          "Longitude": "-122.69411"
        },
        {
          "Latitude": "47.58397",
          "Longitude": "-122.69413"
        },
        {
          "Latitude": "47.58397",
          "Longitude": "-122.69414"
        },
        {
          "Latitude": "47.58397",
          "Longitude": "-122.69415"
        },
        {
          "Latitude": "47.58397",
          "Longitude": "-122.69416"
        },
        {
          "Latitude": "47.58397",
          "Longitude": "-122.69418"
        },
        {
          "Latitude": "47.58397",
          "Longitude": "-122.69419"
        },
        {
          "Latitude": "47.58398",
          "Longitude": "-122.69420"
        },
        {
          "Latitude": "47.58399",
          "Longitude": "-122.69421"
        },
        {
          "Latitude": "47.58399",
          "Longitude": "-122.69421"
        },
        {
          "Latitude": "47.58400",
          "Longitude": "-122.69422"
        },
        {
          "Latitude": "47.58401",
          "Longitude": "-122.69422"
        },
        {
          "Latitude": "47.58402",
          "Longitude": "-122.69422"
        },
        {
          "Latitude": "47.58403",
          "Longitude": "-122.69421"
        },
        {
          "Latitude": "47.58404",
          "Longitude": "-122.69421"
        },
        {
          "Latitude": "47.58404",
          "Longitude": "-122.69420"
        },
        {
          "Latitude": "47.58405",
          "Longitude": "-122.69419"
        },
        {
          "Latitude": "47.58405",
          "Longitude": "-122.69418"
        },
        {
          "Latitude": "47.58405",
          "Longitude": "-122.69417"
        },
        {
          "Latitude": "47.58406",
          "Longitude": "-122.69415"
        },
        {
          "Latitude": "47.58406",
          "Longitude": "-122.69414"
        },
        {
          "Latitude": "47.58405",
          "Longitude": "-122.69413"
        },
        {
          "Latitude": "47.58405",
          "Longitude": "-122.69412"
        },
        {
          "Latitude": "47.58404",
          "Longitude": "-122.69411"
        },
        {
          "Latitude": "47.58404",
          "Longitude": "-122.69410"
        },
        {
          "Latitude": "47.58403",
          "Longitude": "-122.69409"
        },
        {
          "Latitude": "47.58402",
          "Longitude": "-122.69409"
        },
        {
          "Latitude": "47.58401",
          "Longitude": "-122.69409"
        }
      ],
      "BoundingBox": {
        "Min": {
          "Latitude": "47.58397",
          "Longitude": "-122.69422"
        },
        "Max": {
          "Latitude": "47.58406",
          "Longitude": "-122.69409"
        }
      }
    },
    {
      "DataProvider": {
        "Attributes": [
          {
            "Name": "Start time",
            "RefName": "StartDate",
            "Value": "04/07 03:02 PM",
            "RefValue": "",
            "NoDisplay": false
          },
          {
            "Name": "Customers impacted",
            "RefName": "Customers impacted",
            "Value": "4",
            "RefValue": "",
            "NoDisplay": false
          },
          {
            "Name": "Status",
            "RefName": "Status",
            "Value": "Outage reported",
            "RefValue": "Outage reported",
            "NoDisplay": false
          },
          {
            "Name": "Cause",
            "RefName": "Cause",
            "Value": "Under investigation",
            "RefValue": "",
            "NoDisplay": false
          },
          {
            "Name": "Last update",
            "RefName": "LastUpdated",
            "Value": "04/07 03:15 PM",
            "RefValue": "",
            "NoDisplay": false
          },
          {
            "Name": "Est. restoration time",
            "RefName": "Est. Restoration time",
            "Value": "04/07 06:30 PM",
            "RefValue": "",
            "NoDisplay": false
          },
          {
            "Name": "Outage ID",
            "RefName": "OutageEventId",
            "Value": "INC1140118610",
            "RefValue": "",
            "NoDisplay": false
          }
        ],
        "PointOfInterest": {
          "Latitude": "47.56727",
          "Longitude": "-122.64430",
          "MapType": "Outage",
          "PinType": "Outage",
          "OrderType": "Outage",
          "Title": "Bremerton",
          "Id": "INC1140118610",
          "PlannedOutage": false,
          "FilterType": "Outage",
          "IsHve": false
        },
        "CRCAttributes": null
      },
      "Polygon": [
        {
          "Latitude": "47.56708",
          "Longitude": "-122.64421"
        },
        {
          "Latitude": "47.56714",
          "Longitude": "-122.64445"
        },
        {
          "Latitude": "47.56719",
          "Longitude": "-122.64450"
        },
        {
          "Latitude": "47.56751",
          "Longitude": "-122.64435"
        },
        {
          "Latitude": "47.56751",
          "Longitude": "-122.64422"
        },
        {
          "Latitude": "47.56713",
          "Longitude": "-122.64412"
        },
        {
          "Latitude": "47.56708",
          "Longitude": "-122.64421"
        }
      ],
      "BoundingBox": {
        "Min": {
          "Latitude": "47.56708",
          "Longitude": "-122.64450"
        },
        "Max": {
          "Latitude": "47.56751",
          "Longitude": "-122.64412"
        }
      }
    },
    {
      "DataProvider": {
        "Attributes": [
          {
            "Name": "Start time",
            "RefName": "StartDate",
            "Value": "04/07 03:15 PM",
            "RefValue": "",
            "NoDisplay": false
          },
          {
            "Name": "Customers impacted",
            "RefName": "Customers impacted",
            "Value": "3",
            "RefValue": "",
            "NoDisplay": false
          },
          {
            "Name": "Status",
            "RefName": "Status",
            "Value": "Crew onsite",
            "RefValue": "Repair crew onsite",
            "NoDisplay": false
          },
          {
            "Name": "Cause",
            "RefName": "Cause",
            "Value": "Accident",
            "RefValue": "",
            "NoDisplay": false
          },
          {
            "Name": "Last update",
            "RefName": "LastUpdated",
            "Value": "04/07 03:15 PM",
            "RefValue": "",
            "NoDisplay": false
          },
          {
            "Name": "Est. restoration time",
            "RefName": "Est. Restoration time",
            "Value": "04/07 06:30 PM",
            "RefValue": "",
            "NoDisplay": false
          },
          {
            "Name": "Outage ID",
            "RefName": "OutageEventId",
            "Value": "INC1140118234",
            "RefValue": "",
            "NoDisplay": false
          }
        ],
        "PointOfInterest": {
          "Latitude": "47.74612",
          "Longitude": "-122.06466",
          "MapType": "Outage",
          "PinType": "Outage",
          "OrderType": "Crew1 - Outage",
          "Title": "Cottage Lake",
          "Id": "INC1140118234",
          "PlannedOutage": false,
          "FilterType": "Outage",
          "IsHve": false
        },
        "CRCAttributes": null
      },
      "Polygon": [
        {
          "Latitude": "47.74590",
          "Longitude": "-122.06495"
        },
        {
          "Latitude": "47.74660",
          "Longitude": "-122.06468"
        },
        {
          "Latitude": "47.74660",
          "Longitude": "-122.06455"
        },
        {
          "Latitude": "47.74590",
          "Longitude": "-122.06440"
        },
        {
          "Latitude": "47.74585",
          "Longitude": "-122.06447"
        },
        {
          "Latitude": "47.74584",
          "Longitude": "-122.06489"
        },
        {
          "Latitude": "47.74590",
          "Longitude": "-122.06495"
        }
      ],
      "BoundingBox": {
        "Min": {
          "Latitude": "47.74584",
          "Longitude": "-122.06495"
        },
        "Max": {
          "Latitude": "47.74660",
          "Longitude": "-122.06440"
        }
      }
    },
    {
      "DataProvider": {
        "Attributes": [
          {
            "Name": "Start time",
            "RefName": "StartDate",
            "Value": "04/07 08:26 AM",
            "RefValue": "",
            "NoDisplay": false
          },
          {
            "Name": "Customers impacted",
            "RefName": "Customers impacted",
            "Value": "5",
            "RefValue": "",
            "NoDisplay": false
          },
          {
            "Name": "Status",
            "RefName": "Status",
            "Value": "Crew onsite",
            "RefValue": "Repair crew onsite",
            "NoDisplay": false
          },
          {
            "Name": "Cause",
            "RefName": "Cause",
            "Value": "Under investigation",
            "RefValue": "",
            "NoDisplay": false
          },
          {
            "Name": "Last update",
            "RefName": "LastUpdated",
            "Value": "04/07 03:15 PM",
            "RefValue": "",
            "NoDisplay": false
          },
          {
            "Name": "Est. restoration time",
            "RefName": "Est. Restoration time",
            "Value": "04/07 11:30 AM",
            "RefValue": "",
            "NoDisplay": false
          },
          {
            "Name": "Outage ID",
            "RefName": "OutageEventId",
            "Value": "INC1140118163",
            "RefValue": "",
            "NoDisplay": false
          }
        ],
        "PointOfInterest": {
          "Latitude": "47.19937",
          "Longitude": "-122.01991",
          "MapType": "Outage",
          "PinType": "Outage",
          "OrderType": "Switching",
          "Title": "Enumclaw",
          "Id": "INC1140118163",
          "PlannedOutage": true,
          "FilterType": "Planned",
          "IsHve": false
        },
        "CRCAttributes": null
      },
      "Polygon": [
        {
          "Latitude": "47.19898",
          "Longitude": "-122.02027"
        },
        {
          "Latitude": "47.19904",
          "Longitude": "-122.02079"
        },
        {
          "Latitude": "47.19911",
          "Longitude": "-122.02083"
        },
        {
          "Latitude": "47.19959",
          "Longitude": "-122.02046"
        },
        {
          "Latitude": "47.19961",
          "Longitude": "-122.02040"
        },
        {
          "Latitude": "47.19967",
          "Longitude": "-122.01859"
        },
        {
          "Latitude": "47.19959",
          "Longitude": "-122.01855"
        },
        {
          "Latitude": "47.19899",
          "Longitude": "-122.02023"
        },
        {
          "Latitude": "47.19898",
          "Longitude": "-122.02027"
        }
      ],
      "BoundingBox": {
        "Min": {
          "Latitude": "47.19898",
          "Longitude": "-122.02083"
        },
        "Max": {
          "Latitude": "47.19967",
          "Longitude": "-122.01855"
        }
      }
    },
    {
      "DataProvider": {
        "Attributes": [
          {
            "Name": "Start time",
            "RefName": "StartDate",
            "Value": "04/07 08:27 AM",
            "RefValue": "",
            "NoDisplay": false
          },
          {
            "Name": "Customers impacted",
            "RefName": "Customers impacted",
            "Value": "1",
            "RefValue": "",
            "NoDisplay": false
          },
          {
            "Name": "Status",
            "RefName": "Status",
            "Value": "Crew onsite",
            "RefValue": "Repair crew onsite",
            "NoDisplay": false
          },
          {
            "Name": "Cause",
            "RefName": "Cause",
            "Value": "Scheduled outage",
            "RefValue": "",
            "NoDisplay": false
          },
          {
            "Name": "Last update",
            "RefName": "LastUpdated",
            "Value": "04/07 03:15 PM",
            "RefValue": "",
            "NoDisplay": false
          },
          {
            "Name": "Est. restoration time",
            "RefName": "Est. Restoration time",
            "Value": "04/07 12:00 PM",
            "RefValue": "",
            "NoDisplay": false
          },
          {
            "Name": "Outage ID",
            "RefName": "OutageEventId",
            "Value": "INC1140118164",
            "RefValue": "",
            "NoDisplay": false
          }
        ],
        "PointOfInterest": {
          "Latitude": "46.94061",
          "Longitude": "-122.90875",
          "MapType": "Outage",
          "PinType": "Outage",
          "OrderType": "Switching",
          "Title": "Olympia",
          "Id": "INC1140118164",
          "PlannedOutage": true,
          "FilterType": "Planned",
          "IsHve": false
        },
        "CRCAttributes": null
      },
      "Polygon": [
        {
          "Latitude": "46.94061",
          "Longitude": "-122.90868"
        },
        {
          "Latitude": "46.94060",
          "Longitude": "-122.90868"
        },
        {
          "Latitude": "46.94059",
          "Longitude": "-122.90868"
        },
        {
          "Latitude": "46.94058",
          "Longitude": "-122.90869"
        },
        {
          "Latitude": "46.94057",
          "Longitude": "-122.90870"
        },
        {
          "Latitude": "46.94057",
          "Longitude": "-122.90871"
        },
        {
          "Latitude": "46.94056",
          "Longitude": "-122.90872"
        },
        {
          "Latitude": "46.94056",
          "Longitude": "-122.90873"
        },
        {
          "Latitude": "46.94056",
          "Longitude": "-122.90874"
        },
        {
          "Latitude": "46.94056",
          "Longitude": "-122.90876"
        },
        {
          "Latitude": "46.94056",
          "Longitude": "-122.90877"
        },
        {
          "Latitude": "46.94057",
          "Longitude": "-122.90878"
        },
        {
          "Latitude": "46.94057",
          "Longitude": "-122.90879"
        },
        {
          "Latitude": "46.94058",
          "Longitude": "-122.90880"
        },
        {
          "Latitude": "46.94059",
          "Longitude": "-122.90880"
        },
        {
          "Latitude": "46.94060",
          "Longitude": "-122.90881"
        },
        {
          "Latitude": "46.94060",
          "Longitude": "-122.90881"
        },
        {
          "Latitude": "46.94061",
          "Longitude": "-122.90881"
        },
        {
          "Latitude": "46.94062",
          "Longitude": "-122.90881"
        },
        {
          "Latitude": "46.94063",
          "Longitude": "-122.90880"
        },
        {
          "Latitude": "46.94064",
          "Longitude": "-122.90879"
        },
        {
          "Latitude": "46.94064",
          "Longitude": "-122.90878"
        },
        {
          "Latitude": "46.94065",
          "Longitude": "-122.90877"
        },
        {
          "Latitude": "46.94065",
          "Longitude": "-122.90876"
        },
        {
          "Latitude": "46.94065",
          "Longitude": "-122.90875"
        },
        {
          "Latitude": "46.94065",
          "Longitude": "-122.90873"
        },
        {
          "Latitude": "46.94065",
          "Longitude": "-122.90872"
        },
        {
          "Latitude": "46.94064",
          "Longitude": "-122.90871"
        },
        {
          "Latitude": "46.94064",
          "Longitude": "-122.90870"
        },
        {
          "Latitude": "46.94063",
          "Longitude": "-122.90869"
        },
        {
          "Latitude": "46.94062",
          "Longitude": "-122.90868"
        },
        {
          "Latitude": "46.94062",
          "Longitude": "-122.90868"
        },
        {
          "Latitude": "46.94061",
          "Longitude": "-122.90868"
        }
      ],
      "BoundingBox": {
        "Min": {
          "Latitude": "46.94056",
          "Longitude": "-122.90881"
        },
        "Max": {
          "Latitude": "46.94065",
          "Longitude": "-122.90868"
        }
      }
    },
    {
      "DataProvider": {
        "Attributes": [
          {
            "Name": "Start time",
            "RefName": "StartDate",
            "Value": "04/04 08:32 AM",
            "RefValue": "",
            "NoDisplay": false
          },
          {
            "Name": "Customers impacted",
            "RefName": "Customers impacted",
            "Value": "1",
            "RefValue": "",
            "NoDisplay": false
          },
          {
            "Name": "Status",
            "RefName": "Status",
            "Value": "Outage reported",
            "RefValue": "Outage reported",
            "NoDisplay": false
          },
          {
            "Name": "Cause",
            "RefName": "Cause",
            "Value": "Accident",
            "RefValue": "",
            "NoDisplay": false
          },
          {
            "Name": "Last update",
            "RefName": "LastUpdated",
            "Value": "04/07 03:15 PM",
            "RefValue": "",
            "NoDisplay": false
          },
          {
            "Name": "Est. restoration time",
            "RefName": "Est. Restoration time",
            "Value": "04/04 12:30 PM",
            "RefValue": "",
            "NoDisplay": false
          },
          {
            "Name": "Outage ID",
            "RefName": "OutageEventId",
            "Value": "INC1140117732",
            "RefValue": "",
            "NoDisplay": false
          }
        ],
        "PointOfInterest": {
          "Latitude": "47.15995",
          "Longitude": "-122.27139",
          "MapType": "Outage",
          "PinType": "Outage",
          "OrderType": "Outage",
          "Title": "Puyallup",
          "Id": "INC1140117732",
          "PlannedOutage": false,
          "FilterType": "Outage",
          "IsHve": false
        },
        "CRCAttributes": null
      },
      "Polygon": [
        {
          "Latitude": "47.15995",
          "Longitude": "-122.27132"
        },
        {
          "Latitude": "47.15994",
          "Longitude": "-122.27132"
        },
        {
          "Latitude": "47.15993",
          "Longitude": "-122.27132"
        },
        {
          "Latitude": "47.15992",
          "Longitude": "-122.27133"
        },
        {
          "Latitude": "47.15992",
          "Longitude": "-122.27134"
        },
        {
          "Latitude": "47.15991",
          "Longitude": "-122.27135"
        },
        {
          "Latitude": "47.15991",
          "Longitude": "-122.27136"
        },
        {
          "Latitude": "47.15990",
          "Longitude": "-122.27137"
        },
        {
          "Latitude": "47.15990",
          "Longitude": "-122.27138"
        },
        {
          "Latitude": "47.15990",
          "Longitude": "-122.27140"
        },
        {
          "Latitude": "47.15990",
          "Longitude": "-122.27141"
        },
        {
          "Latitude": "47.15991",
          "Longitude": "-122.27142"
        },
        {
          "Latitude": "47.15991",
          "Longitude": "-122.27143"
        },
        {
          "Latitude": "47.15992",
          "Longitude": "-122.27144"
        },
        {
          "Latitude": "47.15993",
          "Longitude": "-122.27145"
        },
        {
          "Latitude": "47.15994",
          "Longitude": "-122.27145"
        },
        {
          "Latitude": "47.15995",
          "Longitude": "-122.27145"
        },
        {
          "Latitude": "47.15995",
          "Longitude": "-122.27145"
        },
        {
          "Latitude": "47.15996",
          "Longitude": "-122.27145"
        },
        {
          "Latitude": "47.15997",
          "Longitude": "-122.27144"
        },
        {
          "Latitude": "47.15998",
          "Longitude": "-122.27143"
        },
        {
          "Latitude": "47.15998",
          "Longitude": "-122.27142"
        },
        {
          "Latitude": "47.15999",
          "Longitude": "-122.27141"
        },
        {
          "Latitude": "47.15999",
          "Longitude": "-122.27140"
        },
        {
          "Latitude": "47.15999",
          "Longitude": "-122.27139"
        },
        {
          "Latitude": "47.15999",
          "Longitude": "-122.27137"
        },
        {
          "Latitude": "47.15999",
          "Longitude": "-122.27136"
        },
        {
          "Latitude": "47.15998",
          "Longitude": "-122.27135"
        },
        {
          "Latitude": "47.15998",
          "Longitude": "-122.27134"
        },
        {
          "Latitude": "47.15997",
          "Longitude": "-122.27133"
        },
        {
          "Latitude": "47.15996",
          "Longitude": "-122.27132"
        },
        {
          "Latitude": "47.15996",
          "Longitude": "-122.27132"
        },
        {
          "Latitude": "47.15995",
          "Longitude": "-122.27132"
        }
      ],
      "BoundingBox": {
        "Min": {
          "Latitude": "47.15990",
          "Longitude": "-122.27145"
        },
        "Max": {
          "Latitude": "47.15999",
          "Longitude": "-122.27132"
        }
      }
    },
    {
      "DataProvider": {
        "Attributes": [
          {
            "Name": "Start time",
            "RefName": "StartDate",
            "Value": "04/07 12:35 PM",
            "RefValue": "",
            "NoDisplay": false
          },
          {
            "Name": "Customers impacted",
            "RefName": "Customers impacted",
            "Value": "1",
            "RefValue": "",
            "NoDisplay": false
          },
          {
            "Name": "Status",
            "RefName": "Status",
            "Value": "Assessing damage",
            "RefValue": "Waiting for repairs",
            "NoDisplay": false
          },
          {
            "Name": "Cause",
            "RefName": "Cause",
            "Value": "Under investigation",
            "RefValue": "",
            "NoDisplay": false
          },
          {
            "Name": "Last update",
            "RefName": "LastUpdated",
            "Value": "04/07 03:15 PM",
            "RefValue": "",
            "NoDisplay": false
          },
          {
            "Name": "Est. restoration time",
            "RefName": "Est. Restoration time",
            "Value": "04/07 04:00 PM",
            "RefValue": "",
            "NoDisplay": false
          },
          {
            "Name": "Outage ID",
            "RefName": "OutageEventId",
            "Value": "INC1140118245",
            "RefValue": "",
            "NoDisplay": false
          }
        ],
        "PointOfInterest": {
          "Latitude": "47.71104",
          "Longitude": "-121.35439",
          "MapType": "Outage",
          "PinType": "Outage",
          "OrderType": "Outage",
          "Title": "Skykomish",
          "Id": "INC1140118245",
          "PlannedOutage": false,
          "FilterType": "Outage",
          "IsHve": false
        },
        "CRCAttributes": null
      },
      "Polygon": [
        {
          "Latitude": "47.71104",
          "Longitude": "-121.35432"
        },
        {
          "Latitude": "47.71104",
          "Longitude": "-121.35432"
        },
        {
          "Latitude": "47.71103",
          "Longitude": "-121.35432"
        },
        {
          "Latitude": "47.71102",
          "Longitude": "-121.35433"
        },
        {
          "Latitude": "47.71101",
          "Longitude": "-121.35434"
        },
        {
          "Latitude": "47.71101",
          "Longitude": "-121.35435"
        },
        {
          "Latitude": "47.71100",
          "Longitude": "-121.35436"
        },
        {
          "Latitude": "47.71100",
          "Longitude": "-121.35437"
        },
        {
          "Latitude": "47.71100",
          "Longitude": "-121.35438"
        },
        {
          "Latitude": "47.71100",
          "Longitude": "-121.35440"
        },
        {
          "Latitude": "47.71100",
          "Longitude": "-121.35441"
        },
        {
          "Latitude": "47.71101",
          "Longitude": "-121.35442"
        },
        {
          "Latitude": "47.71101",
          "Longitude": "-121.35443"
        },
        {
          "Latitude": "47.71102",
          "Longitude": "-121.35444"
        },
        {
          "Latitude": "47.71103",
          "Longitude": "-121.35445"
        },
        {
          "Latitude": "47.71104",
          "Longitude": "-121.35445"
        },
        {
          "Latitude": "47.71104",
          "Longitude": "-121.35445"
        },
        {
          "Latitude": "47.71105",
          "Longitude": "-121.35445"
        },
        {
          "Latitude": "47.71106",
          "Longitude": "-121.35445"
        },
        {
          "Latitude": "47.71107",
          "Longitude": "-121.35444"
        },
        {
          "Latitude": "47.71108",
          "Longitude": "-121.35443"
        },
        {
          "Latitude": "47.71108",
          "Longitude": "-121.35442"
        },
        {
          "Latitude": "47.71109",
          "Longitude": "-121.35441"
        },
        {
          "Latitude": "47.71109",
          "Longitude": "-121.35440"
        },
        {
          "Latitude": "47.71109",
          "Longitude": "-121.35439"
        },
        {
          "Latitude": "47.71109",
          "Longitude": "-121.35437"
        },
        {
          "Latitude": "47.71109",
          "Longitude": "-121.35436"
        },
        {
          "Latitude": "47.71108",
          "Longitude": "-121.35435"
        },
        {
          "Latitude": "47.71108",
          "Longitude": "-121.35434"
        },
        {
          "Latitude": "47.71107",
          "Longitude": "-121.35433"
        },
        {
          "Latitude": "47.71106",
          "Longitude": "-121.35432"
        },
        {
          "Latitude": "47.71105",
          "Longitude": "-121.35432"
        },
        {
          "Latitude": "47.71104",
          "Longitude": "-121.35432"
        }
      ],
      "BoundingBox": {
        "Min": {
          "Latitude": "47.71100",
          "Longitude": "-121.35445"
        },
        "Max": {
          "Latitude": "47.71109",
          "Longitude": "-121.35432"
        }
      }
    },
    {
      "DataProvider": {
        "Attributes": [
          {
            "Name": "Start time",
            "RefName": "StartDate",
            "Value": "04/07 01:05 PM",
            "RefValue": "",
            "NoDisplay": false
          },
          {
            "Name": "Customers impacted",
            "RefName": "Customers impacted",
            "Value": "1",
            "RefValue": "",
            "NoDisplay": false
          },
          {
            "Name": "Status",
            "RefName": "Status",
            "Value": "Crew assigned",
            "RefValue": "Crew assigned",
            "NoDisplay": false
          },
          {
            "Name": "Cause",
            "RefName": "Cause",
            "Value": "Equipment failure",
            "RefValue": "",
            "NoDisplay": false
          },
          {
            "Name": "Last update",
            "RefName": "LastUpdated",
            "Value": "04/07 03:15 PM",
            "RefValue": "",
            "NoDisplay": false
          },
          {
            "Name": "Est. restoration time",
            "RefName": "Est. Restoration time",
            "Value": "04/07 05:30 PM",
            "RefValue": "",
            "NoDisplay": false
          },
          {
            "Name": "Outage ID",
            "RefName": "OutageEventId",
            "Value": "INC1140118572",
            "RefValue": "",
            "NoDisplay": false
          }
        ],
        "PointOfInterest": {
          "Latitude": "47.11809",
          "Longitude": "-122.16667",
          "MapType": "Outage",
          "PinType": "Outage",
          "OrderType": "Crew1 - Outage",
          "Title": "Tehaleh",
          "Id": "INC1140118572",
          "PlannedOutage": false,
          "FilterType": "Outage",
          "IsHve": false
        },
        "CRCAttributes": null
      },
      "Polygon": [
        {
          "Latitude": "47.11809",
          "Longitude": "-122.16661"
        },
        {
          "Latitude": "47.11808",
          "Longitude": "-122.16661"
        },
        {
          "Latitude": "47.11807",
          "Longitude": "-122.16661"
        },
        {
          "Latitude": "47.11806",
          "Longitude": "-122.16662"
        },
        {
          "Latitude": "47.11806",
          "Longitude": "-122.16662"
        },
        {
          "Latitude": "47.11805",
          "Longitude": "-122.16663"
        },
        {
          "Latitude": "47.11805",
          "Longitude": "-122.16665"
        },
        {
          "Latitude": "47.11804",
          "Longitude": "-122.16666"
        },
        {
          "Latitude": "47.11804",
          "Longitude": "-122.16667"
        },
        {
          "Latitude": "47.11804",
          "Longitude": "-122.16668"
        },
        {
          "Latitude": "47.11805",
          "Longitude": "-122.16670"
        },
        {
          "Latitude": "47.11805",
          "Longitude": "-122.16671"
        },
        {
          "Latitude": "47.11806",
          "Longitude": "-122.16672"
        },
        {
          "Latitude": "47.11806",
          "Longitude": "-122.16673"
        },
        {
          "Latitude": "47.11807",
          "Longitude": "-122.16673"
        },
        {
          "Latitude": "47.11808",
          "Longitude": "-122.16674"
        },
        {
          "Latitude": "47.11809",
          "Longitude": "-122.16674"
        },
        {
          "Latitude": "47.11810",
          "Longitude": "-122.16674"
        },
        {
          "Latitude": "47.11810",
          "Longitude": "-122.16673"
        },
        {
          "Latitude": "47.11811",
          "Longitude": "-122.16673"
        },
        {
          "Latitude": "47.11812",
          "Longitude": "-122.16672"
        },
        {
          "Latitude": "47.11812",
          "Longitude": "-122.16671"
        },
        {
          "Latitude": "47.11813",
          "Longitude": "-122.16670"
        },
        {
          "Latitude": "47.11813",
          "Longitude": "-122.16669"
        },
        {
          "Latitude": "47.11813",
          "Longitude": "-122.16667"
        },
        {
          "Latitude": "47.11813",
          "Longitude": "-122.16666"
        },
        {
          "Latitude": "47.11813",
          "Longitude": "-122.16665"
        },
        {
          "Latitude": "47.11813",
          "Longitude": "-122.16664"
        },
        {
          "Latitude": "47.11812",
          "Longitude": "-122.16663"
        },
        {
          "Latitude": "47.11811",
          "Longitude": "-122.16662"
        },
        {
          "Latitude": "47.11811",
          "Longitude": "-122.16661"
        },
        {
          "Latitude": "47.11810",
          "Longitude": "-122.16661"
        },
        {
          "Latitude": "47.11809",
          "Longitude": "-122.16661"
        }
      ],
      "BoundingBox": {
        "Min": {
          "Latitude": "47.11804",
          "Longitude": "-122.16674"
        },
        "Max": {
          "Latitude": "47.11813",
          "Longitude": "-122.16661"
        }
      }
    }
  ],
  "LastUpdated": "2026-04-07T22:19:07.3576944+00:00"
}
